{"PartyRoleInvestmentJurisdictionArray":[{"Jur":{"JurTyp":"Country","JurCd":"GB"}}],"OrganizationInformation":{"CompanyNumberExternalIdentificationArray":[{"CoNumExtIdnAttriTyp":"CMPNY_CD","CoNumExtIdnValTxt":"092","SrcSysTyp":"ICON"}]},"PartyRoleExternalIdentificationArray":[{"PtyRlExtIdnAttriTyp":"PARTY","PtyRlExtIdnValTxt":"80476225","SrcSysTyp":"ICON"}],"PartyRoleAML":{"AIFMDRgstTyp":"NFCO","LstTrigDt":"2019-11-14","WorldChkRqmntTyp":"0001","DueDilInd":"Y","DueDilTyp":"0002"},"PartyRoleAMLJurisdictionArray":[{"CmpltStatInd":"Y","RvwExmtInd":"Y","RvwExmtRsnCd":"UC","Jur":{"JurTyp":"Country","JurCd":"GB"},"RskLvlNmTxt":"Medium","RskRtTyp":"Medium"}],"UBERPtyRlID":"00000000-0000-0000-0000-000000000000","PtyRlIdTxt":"102020180476225","PtyTyp":"Organisation","RlTyp":"Investor","KeyNmTxt":"Acme Anvil Pension Scheme Limited","CtgryTyp":"Investor","CltAMLRstctInd":"Y","ClssTyp":"X","DtaErsCd":"NA","DfltLangCd":"ENG","DomCntryCd":"GB","FstKnwnDt":"2019-11-13","FstSubscrAmt":0E-10,"LglEntUBERPtyRlId":"00000000-0000-0000-0000-000000000000","RetInvsrInd":"N","VsningFlds":{"VerNum":1,"VerStatTyp":"Published","EntyChnlTyp":"Migrated","SrcSysTyp":"ICON"},"LglEntPtyRlIdTxt":"102010080476225","RlSubTyp":"Pension"}