{"FundPartyRoles":[{"UBERFundPartyRoleId":"00000000-0000-0000-0000-000000000000","FundPartyRoleIdentifierText":"102081080463111","FundPartyRoleFullNameText":"Northern Trust Company Limited Fund Party Role","FundPartyRoleType":"PlanManager","FundPartyRolePartyType":"Organisation","FundPartyRoleDomicileCountryCode":"GB","FundPartyRoleRegulatoryAuthorityType":"FCA","FundPartyRoleClientContactNameText":"Northern Trust Company Limited Fund Party Role","FundPartyRoleRegistrationNameText":"Northern Trust Company Limited Fund Party Role","FundPartyRoleStatusType":"1","FundPartyRoleExternalIdentificationArray":[{"FundPartyRoleExternalIdentificationAttributeType":"PlanManagerId","FundPartyRoleExternalIdentificationLegacyCodeFlag":true,"FundPartyRoleExternalIdentificationValueText":"80463111","SystemType":"ICON"}],"ServiceLineArray":[{"ServiceLineType":"TransferAgency","ServiceLineClassificationType":"TAOnshore","SequenceId":1700}],"CompanyEnvironmentArray":[{"CompanyEnvironmentExternalIdentificationValueText":"093","CompanyEnvironmentNameText":"New Management Company - irl093","SequenceId":1301}],"ContactPointArray":[{"PrimaryContactIndicator":"Y","ContactType":"HM","AlternateLanguageCode":"ENG","PreferredMethodType":"Postal Mail","SequenceId":31968956,"PhysicalAddress":{"AttentionNameText":"Northern Trust Company Limited Fund Party Role","Line1Text":"amendABCDE12345","Line2Text":"amendDEFGH67890","Line3Text":"amendGHIJK12345","Line4Text":"JKLMN67890","PostalOfficeCodeText":"333","CountryCode":"GB","SequenceId":1101,"PhysicalAddressContactType":"HM"}}],"Jurisdiction":{"JurisdictionType":"Country","JurisdictionCode":"GB"},"VersioningFields":{"VersionNumber":1,"VersionStatusType":"Published","EntryChannelType":"Migrated","SystemType":"ICON"}}]}